manga2pdf/__init__.py
manga2pdf/manga2pdf.py
manga2pdf/manga2pdf_gui.py
manga2pdf/locales/de_DE.yml
manga2pdf/locales/en_US.yml
manga2pdf/locales/es_ES.yml
manga2pdf/locales/fr_FR.yml
manga2pdf/locales/ja_JP.yml
manga2pdf/locales/zh_CN.yml
manga2pdf/locales/zh_TW.yml
manga2pdf-0.3.1.dist-info/licenses/LICENSE
manga2pdf-0.3.1.dist-info/METADATA
manga2pdf-0.3.1.dist-info/PKG-INFO (ThinkCentre の競合コピー 2025-08-06)
manga2pdf-0.3.1.dist-info/WHEEL
manga2pdf-0.3.1.dist-info/entry_points.txt
manga2pdf-0.3.1.dist-info/top_level.txt
manga2pdf-0.3.1.dist-info/RECORD
