Metadata-Version: 2.4
Name: manga2pdf
Version: 0.3.1
Summary: Convert manga/comic files(zip, epub, etc.) or directory containing image files (jpg, png, etc.) to PDF.
Author: mashu3
License: MIT
Project-URL: Homepage, https://github.com/mashu3/manga2pdf
Keywords: manga,comic,pdf,converter
Classifier: License :: OSI Approved :: MIT License
Classifier: Programming Language :: Python :: 3.9
Classifier: Programming Language :: Python :: 3.10
Classifier: Programming Language :: Python :: 3.11
Classifier: Programming Language :: Python :: 3.12
Classifier: Programming Language :: Python :: 3.13
Requires-Python: >=3.7
License-File: LICENSE
Requires-Dist: lxml
Requires-Dist: numpy
Requires-Dist: img2pdf
Requires-Dist: Pillow
Requires-Dist: pikepdf
Requires-Dist: rarfile
Requires-Dist: py7zr
Requires-Dist: i18nice[YAML]
Requires-Dist: tkface
Provides-Extra: windows
Requires-Dist: win32_setctime; extra == "windows"
Dynamic: license-file
